testbeds/__init__.py
testbeds/api/__init__.py
testbeds/api/client.py
testbeds/api/main.py
testbeds/api/manager.py
testbeds/api/template/pod_template.yaml
testbeds/api/template/service_template.yaml
testbeds/exceptions.py
testbeds/schema.py
testbeds/sdk/__init__.py
testbeds/sdk/async_client.py
testbeds/sdk/base_client.py
testbeds/sdk/client.py
testbeds/sdk/exceptions.py
testbeds/sdk/sdk.py
testbeds/sdk/task_monitor.py
testbeds/swebench/__init__.py
testbeds/swebench/constants.py
testbeds/swebench/grading.py
testbeds/swebench/log_parsers.py
testbeds/swebench/test_spec.py
testbeds/swebench/utils.py
testbeds/testbed/__init__.py
testbeds/testbed/container.py
testbeds/testbed/kubernetes.py
testbeds/testbed/server.py
moatless_testbeds-0.0.17.dist-info/LICENSE
moatless_testbeds-0.0.17.dist-info/METADATA
moatless_testbeds-0.0.17.dist-info/WHEEL
moatless_testbeds-0.0.17.dist-info/RECORD
